easyx509deserialization/__init__.py
easyx509deserialization/read_certificate.py
easyx509deserialization-0.9.2.dist-info/METADATA
easyx509deserialization-0.9.2.dist-info/WHEEL
easyx509deserialization-0.9.2.dist-info/license_files/LICENSE
easyx509deserialization-0.9.2.dist-info/RECORD
