Metadata-Version: 2.1
Name: easyx509deserialization
Version: 0.9.2
Summary: A front end to the cryptography package to easily extract information from an x509 certificate
Project-URL: Homepage, https://github.com/notthatadam/easyx509deserialization
Project-URL: Bug Tracker, https://github.com/notthatadam/easyx509deserialization/issues
Author-email: Adam Peterson <adampeterson@gmail.com>
License: License: GNU General Public License v3 (GPLv3) (GNU GENERAL PUBLIC LICENSE Version 3)
Classifier: Development Status :: 4 - Beta
Classifier: Intended Audience :: Developers
Classifier: Intended Audience :: System Administrators
Classifier: License :: OSI Approved :: GNU General Public License v3 (GPLv3)
Classifier: Programming Language :: Python :: 3
Classifier: Programming Language :: Python :: 3.10
Classifier: Programming Language :: Python :: 3.11
Classifier: Programming Language :: Python :: 3.12
Classifier: Programming Language :: Python :: 3.6
Classifier: Programming Language :: Python :: 3.7
Classifier: Programming Language :: Python :: 3.8
Classifier: Programming Language :: Python :: 3.9
Requires-Python: >=3.6
